DownloadKit/__init__.py
DownloadKit/_funcs.py
DownloadKit/_funcs.pyi
DownloadKit/downloadKit.py
DownloadKit/downloadKit.pyi
DownloadKit/mission.py
DownloadKit/mission.pyi
DownloadKit/setter.py
DownloadKit/setter.pyi
DownloadKit-2.0.7.dist-info/LICENSE
DownloadKit-2.0.7.dist-info/METADATA
DownloadKit-2.0.7.dist-info/WHEEL
DownloadKit-2.0.7.dist-info/top_level.txt
DownloadKit-2.0.7.dist-info/RECORD
